{
    "cand_form": "C18H24N2O5",
    "cand_ion": "[M+H]+",
    "output_tbl": {
        "mz": [
            70.0651,
            102.055,
            116.0706,
            117.0699,
            134.0964,
            160.1121,
            161.1172,
            178.1226,
            206.1176,
            207.1227,
            303.1703,
            304.1781,
            349.1337
        ],
        "ms2_inten": [
            0.014655549100380432,
            0.21174243190055148,
            0.1175600906657532,
            0.09457304357014332,
            0.08345584602995922,
            0.2926653358748837,
            0.019939036741220762,
            0.027890380954088446,
            1.0,
            0.08209758584503435,
            0.17701603320545475,
            0.02833946367285562,
            0.036499376692019865
        ],
        "mono_mass": [
            70.0651,
            102.055,
            116.0706,
            117.0699,
            134.0964,
            160.1121,
            161.1172,
            178.1226,
            206.1176,
            207.1227,
            303.1703,
            304.1781,
            349.1337
        ],
        "abs_mass_diff": [
            0.0,
            0.0,
            0.0,
            0.0,
            0.0,
            0.0,
            0.0,
            0.0,
            0.0,
            0.0,
            0.0,
            0.0,
            0.0
        ],
        "mass_diff": [
            0.0,
            0.0,
            0.0,
            0.0,
            0.0,
            0.0,
            0.0,
            0.0,
            0.0,
            0.0,
            0.0,
            0.0,
            0.0
        ],
        "formula": [
            "C18H24N2O5",
            "C18H24N2O5",
            "C18H24N2O5",
            "C18H24N2O5",
            "C18H24N2O5",
            "C18H24N2O5",
            "C18H24N2O5",
            "C18H24N2O5",
            "C18H24N2O5",
            "C18H24N2O5",
            "C18H24N2O5",
            "C18H24N2O5",
            "C18H24N2O5"
        ],
        "ions": [
            "[M+H]+",
            "[M+H]+",
            "[M+H]+",
            "[M+H]+",
            "[M+H]+",
            "[M+H]+",
            "[M+H]+",
            "[M+H]+",
            "[M+H]+",
            "[M+H]+",
            "[M+H]+",
            "[M+H]+",
            "[M+H]+"
        ]
    }
}