{
    "cand_form": "C19H23ClN4O3",
    "cand_ion": "[M+H]+",
    "output_tbl": {
        "mz": [
            69.0447,
            78.9945,
            97.076,
            120.0444,
            121.0284,
            166.0975,
            192.0772,
            201.0533,
            216.0768,
            241.072,
            255.0877,
            256.0955,
            257.1397,
            268.1081,
            284.0904,
            285.1346,
            313.1295,
            314.1306
        ],
        "ms2_inten": [
            0.12886784471140258,
            0.12228189154158625,
            0.06431317933849987,
            0.08404322002365983,
            0.08083278272623945,
            0.21617621509902524,
            0.05478057582436622,
            0.07119033886626892,
            0.06129086859704011,
            0.08370528159129652,
            0.11013924471736726,
            0.3379834336201579,
            0.1139175307144673,
            0.11789677646618296,
            0.10725811395442524,
            0.6156259512099983,
            1.0,
            0.11695793367720092
        ],
        "mono_mass": [
            69.0447,
            78.9945,
            97.076,
            120.0444,
            121.0284,
            166.0975,
            192.0772,
            201.0533,
            216.0768,
            241.072,
            255.0877,
            256.0955,
            257.1397,
            268.1081,
            284.0904,
            285.1346,
            313.1295,
            314.1306
        ],
        "abs_mass_diff": [
            0.0,
            0.0,
            0.0,
            0.0,
            0.0,
            0.0,
            0.0,
            0.0,
            0.0,
            0.0,
            0.0,
            0.0,
            0.0,
            0.0,
            0.0,
            0.0,
            0.0,
            0.0
        ],
        "mass_diff": [
            0.0,
            0.0,
            0.0,
            0.0,
            0.0,
            0.0,
            0.0,
            0.0,
            0.0,
            0.0,
            0.0,
            0.0,
            0.0,
            0.0,
            0.0,
            0.0,
            0.0,
            0.0
        ],
        "formula": [
            "C19H23ClN4O3",
            "C19H23ClN4O3",
            "C19H23ClN4O3",
            "C19H23ClN4O3",
            "C19H23ClN4O3",
            "C19H23ClN4O3",
            "C19H23ClN4O3",
            "C19H23ClN4O3",
            "C19H23ClN4O3",
            "C19H23ClN4O3",
            "C19H23ClN4O3",
            "C19H23ClN4O3",
            "C19H23ClN4O3",
            "C19H23ClN4O3",
            "C19H23ClN4O3",
            "C19H23ClN4O3",
            "C19H23ClN4O3",
            "C19H23ClN4O3"
        ],
        "ions": [
            "[M+H]+",
            "[M+H]+",
            "[M+H]+",
            "[M+H]+",
            "[M+H]+",
            "[M+H]+",
            "[M+H]+",
            "[M+H]+",
            "[M+H]+",
            "[M+H]+",
            "[M+H]+",
            "[M+H]+",
            "[M+H]+",
            "[M+H]+",
            "[M+H]+",
            "[M+H]+",
            "[M+H]+",
            "[M+H]+"
        ]
    }
}