{
    "cand_form": "C22H23NO4",
    "cand_ion": "[M+H]+",
    "output_tbl": {
        "mz": [
            91.0542,
            201.042,
            219.0526,
            233.0683,
            242.0812,
            260.0917,
            334.1438,
            335.1516,
            352.1543,
            353.1622,
            366.17,
            367.174
        ],
        "ms2_inten": [
            0.22737687185292954,
            0.03196526907531285,
            0.04931068913436494,
            0.026002772952024588,
            0.012660503745596938,
            0.02667256473163069,
            0.3446761590422568,
            0.05234571002448317,
            1.0,
            0.1545935567159776,
            0.23305071369317623,
            0.03934314950365483
        ],
        "mono_mass": [
            91.0542,
            201.042,
            219.0526,
            233.0683,
            242.0812,
            260.0917,
            334.1438,
            335.1516,
            352.1543,
            353.1622,
            366.17,
            367.174
        ],
        "abs_mass_diff": [
            0.0,
            0.0,
            0.0,
            0.0,
            0.0,
            0.0,
            0.0,
            0.0,
            0.0,
            0.0,
            0.0,
            0.0
        ],
        "mass_diff": [
            0.0,
            0.0,
            0.0,
            0.0,
            0.0,
            0.0,
            0.0,
            0.0,
            0.0,
            0.0,
            0.0,
            0.0
        ],
        "formula": [
            "C22H23NO4",
            "C22H23NO4",
            "C22H23NO4",
            "C22H23NO4",
            "C22H23NO4",
            "C22H23NO4",
            "C22H23NO4",
            "C22H23NO4",
            "C22H23NO4",
            "C22H23NO4",
            "C22H23NO4",
            "C22H23NO4"
        ],
        "ions": [
            "[M+H]+",
            "[M+H]+",
            "[M+H]+",
            "[M+H]+",
            "[M+H]+",
            "[M+H]+",
            "[M+H]+",
            "[M+H]+",
            "[M+H]+",
            "[M+H]+",
            "[M+H]+",
            "[M+H]+"
        ]
    }
}