{
    "cand_form": "C14H15ClN4O3",
    "cand_ion": "[M-H]-",
    "output_tbl": {
        "mz": [
            0.0,
            70.3784,
            100.0431,
            128.2671,
            181.4766,
            183.914,
            227.7139
        ],
        "ms2_inten": [
            0.5654269966207303,
            0.3963211566586665,
            0.378518108152953,
            0.4416189667068939,
            0.40060259261710707,
            1.0,
            0.5027341529294107
        ],
        "mono_mass": [
            0.0,
            70.3784,
            100.0431,
            128.2671,
            181.4766,
            183.914,
            227.7139
        ],
        "abs_mass_diff": [
            0.0,
            0.0,
            0.0,
            0.0,
            0.0,
            0.0,
            0.0
        ],
        "mass_diff": [
            0.0,
            0.0,
            0.0,
            0.0,
            0.0,
            0.0,
            0.0
        ],
        "formula": [
            "C14H15ClN4O3",
            "C14H15ClN4O3",
            "C14H15ClN4O3",
            "C14H15ClN4O3",
            "C14H15ClN4O3",
            "C14H15ClN4O3",
            "C14H15ClN4O3"
        ],
        "ions": [
            "[M-H]-",
            "[M-H]-",
            "[M-H]-",
            "[M-H]-",
            "[M-H]-",
            "[M-H]-",
            "[M-H]-"
        ]
    }
}