{
    "cand_form": "C16H17BrClN3O3",
    "cand_ion": "[M+H]+",
    "output_tbl": {
        "mz": [
            67.0417,
            82.0651,
            95.0491,
            100.0757,
            110.0964,
            120.0808,
            121.0648,
            138.0913,
            240.917,
            258.9268,
            396.0111,
            414.0216,
            415.0244
        ],
        "ms2_inten": [
            0.05071081811196817,
            0.15963610567820788,
            0.0744586603517049,
            1.0,
            0.09822625595610626,
            0.31161688169061286,
            0.29939790892781654,
            0.3712596602716104,
            0.04937606065822601,
            0.038500867035123156,
            0.2840669196822624,
            0.6976587873235812,
            0.08514092617073492
        ],
        "mono_mass": [
            67.0417,
            82.0651,
            95.0491,
            100.0757,
            110.0964,
            120.0808,
            121.0648,
            138.0913,
            240.917,
            258.9268,
            396.0111,
            414.0216,
            415.0244
        ],
        "abs_mass_diff": [
            0.0,
            0.0,
            0.0,
            0.0,
            0.0,
            0.0,
            0.0,
            0.0,
            0.0,
            0.0,
            0.0,
            0.0,
            0.0
        ],
        "mass_diff": [
            0.0,
            0.0,
            0.0,
            0.0,
            0.0,
            0.0,
            0.0,
            0.0,
            0.0,
            0.0,
            0.0,
            0.0,
            0.0
        ],
        "formula": [
            "C16H17BrClN3O3",
            "C16H17BrClN3O3",
            "C16H17BrClN3O3",
            "C16H17BrClN3O3",
            "C16H17BrClN3O3",
            "C16H17BrClN3O3",
            "C16H17BrClN3O3",
            "C16H17BrClN3O3",
            "C16H17BrClN3O3",
            "C16H17BrClN3O3",
            "C16H17BrClN3O3",
            "C16H17BrClN3O3",
            "C16H17BrClN3O3"
        ],
        "ions": [
            "[M+H]+",
            "[M+H]+",
            "[M+H]+",
            "[M+H]+",
            "[M+H]+",
            "[M+H]+",
            "[M+H]+",
            "[M+H]+",
            "[M+H]+",
            "[M+H]+",
            "[M+H]+",
            "[M+H]+",
            "[M+H]+"
        ]
    }
}