{
    "cand_form": "C15H13N3O3S",
    "cand_ion": "[M-H]-",
    "output_tbl": {
        "mz": [
            59.0139,
            61.9884,
            91.0223,
            216.07,
            218.0645,
            230.9784,
            231.9822,
            232.9789,
            237.0214,
            271.9686,
            281.9518,
            313.0805,
            314.0843
        ],
        "ms2_inten": [
            0.2564371170490889,
            0.04553275986577926,
            0.04103624509270941,
            0.12812354305312257,
            0.03485327631569963,
            0.039357061239872204,
            0.05559742442125299,
            1.0,
            0.04095899973724299,
            0.031050987288975884,
            0.038351004958390424,
            0.28308190154338925,
            0.07448196120775091
        ],
        "mono_mass": [
            59.0139,
            61.9884,
            91.0223,
            216.07,
            218.0645,
            230.9784,
            231.9822,
            232.9789,
            237.0214,
            271.9686,
            281.9518,
            313.0805,
            314.0843
        ],
        "abs_mass_diff": [
            0.0,
            0.0,
            0.0,
            0.0,
            0.0,
            0.0,
            0.0,
            0.0,
            0.0,
            0.0,
            0.0,
            0.0,
            0.0
        ],
        "mass_diff": [
            0.0,
            0.0,
            0.0,
            0.0,
            0.0,
            0.0,
            0.0,
            0.0,
            0.0,
            0.0,
            0.0,
            0.0,
            0.0
        ],
        "formula": [
            "C15H13N3O3S",
            "C15H13N3O3S",
            "C15H13N3O3S",
            "C15H13N3O3S",
            "C15H13N3O3S",
            "C15H13N3O3S",
            "C15H13N3O3S",
            "C15H13N3O3S",
            "C15H13N3O3S",
            "C15H13N3O3S",
            "C15H13N3O3S",
            "C15H13N3O3S",
            "C15H13N3O3S"
        ],
        "ions": [
            "[M-H]-",
            "[M-H]-",
            "[M-H]-",
            "[M-H]-",
            "[M-H]-",
            "[M-H]-",
            "[M-H]-",
            "[M-H]-",
            "[M-H]-",
            "[M-H]-",
            "[M-H]-",
            "[M-H]-",
            "[M-H]-"
        ]
    }
}