{
    "cand_form": "C29H53NO5",
    "cand_ion": "[M+H]+",
    "output_tbl": {
        "mz": [
            0.0,
            67.0542,
            69.0699,
            71.0855,
            81.0699,
            83.0855,
            86.0964,
            95.0855,
            97.1012,
            109.1012,
            111.1168,
            114.0913,
            123.1168,
            132.1019,
            137.1325,
            142.0863,
            151.1481,
            160.0968,
            167.143,
            179.143,
            191.1794,
            193.1951,
            227.7408,
            291.3046,
            301.289,
            319.2995,
            320.3074
        ],
        "ms2_inten": [
            0.07868470503279679,
            0.13539325930821824,
            0.36870254495204746,
            0.06592296668611458,
            0.3051750298708382,
            0.2678425951463129,
            0.10231679042376314,
            0.3902152924112615,
            0.3022192494149708,
            0.34663950878676464,
            0.11367028103270747,
            1.0,
            0.21418018447624373,
            0.20691994910631084,
            0.16660116873893252,
            0.25295755669692244,
            0.12246040205054803,
            0.3203980846861908,
            0.07144576148745839,
            0.18263609259078645,
            0.0893330971470985,
            0.22257384618379916,
            0.06977622177010863,
            0.16424626525710329,
            0.22496065280042166,
            0.5284233170900318,
            0.0655808497408026
        ],
        "mono_mass": [
            0.0,
            67.0542,
            69.0699,
            71.0855,
            81.0699,
            83.0855,
            86.0964,
            95.0855,
            97.1012,
            109.1012,
            111.1168,
            114.0913,
            123.1168,
            132.1019,
            137.1325,
            142.0863,
            151.1481,
            160.0968,
            167.143,
            179.143,
            191.1794,
            193.1951,
            227.7408,
            291.3046,
            301.289,
            319.2995,
            320.3074
        ],
        "abs_mass_diff": [
            0.0,
            0.0,
            0.0,
            0.0,
            0.0,
            0.0,
            0.0,
            0.0,
            0.0,
            0.0,
            0.0,
            0.0,
            0.0,
            0.0,
            0.0,
            0.0,
            0.0,
            0.0,
            0.0,
            0.0,
            0.0,
            0.0,
            0.0,
            0.0,
            0.0,
            0.0,
            0.0
        ],
        "mass_diff": [
            0.0,
            0.0,
            0.0,
            0.0,
            0.0,
            0.0,
            0.0,
            0.0,
            0.0,
            0.0,
            0.0,
            0.0,
            0.0,
            0.0,
            0.0,
            0.0,
            0.0,
            0.0,
            0.0,
            0.0,
            0.0,
            0.0,
            0.0,
            0.0,
            0.0,
            0.0,
            0.0
        ],
        "formula": [
            "C29H53NO5",
            "C29H53NO5",
            "C29H53NO5",
            "C29H53NO5",
            "C29H53NO5",
            "C29H53NO5",
            "C29H53NO5",
            "C29H53NO5",
            "C29H53NO5",
            "C29H53NO5",
            "C29H53NO5",
            "C29H53NO5",
            "C29H53NO5",
            "C29H53NO5",
            "C29H53NO5",
            "C29H53NO5",
            "C29H53NO5",
            "C29H53NO5",
            "C29H53NO5",
            "C29H53NO5",
            "C29H53NO5",
            "C29H53NO5",
            "C29H53NO5",
            "C29H53NO5",
            "C29H53NO5",
            "C29H53NO5",
            "C29H53NO5"
        ],
        "ions": [
            "[M+H]+",
            "[M+H]+",
            "[M+H]+",
            "[M+H]+",
            "[M+H]+",
            "[M+H]+",
            "[M+H]+",
            "[M+H]+",
            "[M+H]+",
            "[M+H]+",
            "[M+H]+",
            "[M+H]+",
            "[M+H]+",
            "[M+H]+",
            "[M+H]+",
            "[M+H]+",
            "[M+H]+",
            "[M+H]+",
            "[M+H]+",
            "[M+H]+",
            "[M+H]+",
            "[M+H]+",
            "[M+H]+",
            "[M+H]+",
            "[M+H]+",
            "[M+H]+",
            "[M+H]+"
        ]
    }
}