{
    "cand_form": "C22H19N3O4",
    "cand_ion": "[M+H]+",
    "output_tbl": {
        "mz": [
            0.0,
            95.0491,
            115.0542,
            130.0651,
            135.0441,
            169.076,
            176.0621,
            189.0699,
            191.073,
            203.073,
            204.0808,
            205.0846
        ],
        "ms2_inten": [
            0.17655040613255432,
            0.09299275211672209,
            0.2663312990706942,
            0.07355441076018403,
            0.06912169025929846,
            0.11383516161605253,
            0.06326100243261049,
            0.054164758736878475,
            0.08753262492440278,
            0.16134121108093222,
            1.0,
            0.1087006053177243
        ],
        "mono_mass": [
            0.0,
            95.0491,
            115.0542,
            130.0651,
            135.0441,
            169.076,
            176.0621,
            189.0699,
            191.073,
            203.073,
            204.0808,
            205.0846
        ],
        "abs_mass_diff": [
            0.0,
            0.0,
            0.0,
            0.0,
            0.0,
            0.0,
            0.0,
            0.0,
            0.0,
            0.0,
            0.0,
            0.0
        ],
        "mass_diff": [
            0.0,
            0.0,
            0.0,
            0.0,
            0.0,
            0.0,
            0.0,
            0.0,
            0.0,
            0.0,
            0.0,
            0.0
        ],
        "formula": [
            "C22H19N3O4",
            "C22H19N3O4",
            "C22H19N3O4",
            "C22H19N3O4",
            "C22H19N3O4",
            "C22H19N3O4",
            "C22H19N3O4",
            "C22H19N3O4",
            "C22H19N3O4",
            "C22H19N3O4",
            "C22H19N3O4",
            "C22H19N3O4"
        ],
        "ions": [
            "[M+H]+",
            "[M+H]+",
            "[M+H]+",
            "[M+H]+",
            "[M+H]+",
            "[M+H]+",
            "[M+H]+",
            "[M+H]+",
            "[M+H]+",
            "[M+H]+",
            "[M+H]+",
            "[M+H]+"
        ]
    }
}