{
    "cand_form": "C22H29N5O4S",
    "cand_ion": "[M+H]+",
    "output_tbl": {
        "mz": [
            0.0,
            51.0229,
            53.0386,
            54.0338,
            56.0495,
            63.0229,
            65.0386,
            66.0338,
            67.0053,
            67.0417,
            68.0131,
            68.0495,
            69.0447,
            78.0338,
            80.0495,
            93.0447,
            94.0525,
            227.7339
        ],
        "ms2_inten": [
            0.09887511657039437,
            0.08892822924798105,
            0.08413197848064183,
            0.3405535426102246,
            0.07823405193549589,
            0.1214618728113272,
            0.07972020780328556,
            0.11377734676449575,
            0.05666566788949739,
            0.10276149770991856,
            1.0,
            0.06751288733642895,
            0.12217180689792845,
            0.06550722390966443,
            0.10680204256153007,
            0.3640121658263512,
            0.06810923491638532,
            0.08983884386532397
        ],
        "mono_mass": [
            0.0,
            51.0229,
            53.0386,
            54.0338,
            56.0495,
            63.0229,
            65.0386,
            66.0338,
            67.0053,
            67.0417,
            68.0131,
            68.0495,
            69.0447,
            78.0338,
            80.0495,
            93.0447,
            94.0525,
            227.7339
        ],
        "abs_mass_diff": [
            0.0,
            0.0,
            0.0,
            0.0,
            0.0,
            0.0,
            0.0,
            0.0,
            0.0,
            0.0,
            0.0,
            0.0,
            0.0,
            0.0,
            0.0,
            0.0,
            0.0,
            0.0
        ],
        "mass_diff": [
            0.0,
            0.0,
            0.0,
            0.0,
            0.0,
            0.0,
            0.0,
            0.0,
            0.0,
            0.0,
            0.0,
            0.0,
            0.0,
            0.0,
            0.0,
            0.0,
            0.0,
            0.0
        ],
        "formula": [
            "C22H29N5O4S",
            "C22H29N5O4S",
            "C22H29N5O4S",
            "C22H29N5O4S",
            "C22H29N5O4S",
            "C22H29N5O4S",
            "C22H29N5O4S",
            "C22H29N5O4S",
            "C22H29N5O4S",
            "C22H29N5O4S",
            "C22H29N5O4S",
            "C22H29N5O4S",
            "C22H29N5O4S",
            "C22H29N5O4S",
            "C22H29N5O4S",
            "C22H29N5O4S",
            "C22H29N5O4S",
            "C22H29N5O4S"
        ],
        "ions": [
            "[M+H]+",
            "[M+H]+",
            "[M+H]+",
            "[M+H]+",
            "[M+H]+",
            "[M+H]+",
            "[M+H]+",
            "[M+H]+",
            "[M+H]+",
            "[M+H]+",
            "[M+H]+",
            "[M+H]+",
            "[M+H]+",
            "[M+H]+",
            "[M+H]+",
            "[M+H]+",
            "[M+H]+",
            "[M+H]+"
        ]
    }
}