{
    "cand_form": "C16H16ClN3O3S",
    "cand_ion": "[M+H]+",
    "output_tbl": {
        "mz": [
            65.0386,
            90.0464,
            91.0542,
            92.058,
            105.0699,
            117.0573,
            118.0651,
            130.0651,
            132.0808
        ],
        "ms2_inten": [
            0.3480956021253241,
            0.04497206097195898,
            1.0,
            0.047180698902239054,
            0.05374704335168863,
            0.5919015931116783,
            0.10408100492360248,
            0.029664785570989623,
            0.06311342897543676
        ],
        "mono_mass": [
            65.0386,
            90.0464,
            91.0542,
            92.058,
            105.0699,
            117.0573,
            118.0651,
            130.0651,
            132.0808
        ],
        "abs_mass_diff": [
            0.0,
            0.0,
            0.0,
            0.0,
            0.0,
            0.0,
            0.0,
            0.0,
            0.0
        ],
        "mass_diff": [
            0.0,
            0.0,
            0.0,
            0.0,
            0.0,
            0.0,
            0.0,
            0.0,
            0.0
        ],
        "formula": [
            "C16H16ClN3O3S",
            "C16H16ClN3O3S",
            "C16H16ClN3O3S",
            "C16H16ClN3O3S",
            "C16H16ClN3O3S",
            "C16H16ClN3O3S",
            "C16H16ClN3O3S",
            "C16H16ClN3O3S",
            "C16H16ClN3O3S"
        ],
        "ions": [
            "[M+H]+",
            "[M+H]+",
            "[M+H]+",
            "[M+H]+",
            "[M+H]+",
            "[M+H]+",
            "[M+H]+",
            "[M+H]+",
            "[M+H]+"
        ]
    }
}