{
    "cand_form": "C15H15NO2",
    "cand_ion": "[M-H]-",
    "output_tbl": {
        "mz": [
            0.0,
            92.0506,
            103.7112,
            120.4452,
            137.2597,
            153.1072,
            227.712
        ],
        "ms2_inten": [
            0.20981820703311196,
            1.0,
            0.0742517365113274,
            0.07641180689938934,
            0.07567543241726601,
            0.06591803427744322,
            0.0945414030405365
        ],
        "mono_mass": [
            0.0,
            92.0506,
            103.7112,
            120.4452,
            137.2597,
            153.1072,
            227.712
        ],
        "abs_mass_diff": [
            0.0,
            0.0,
            0.0,
            0.0,
            0.0,
            0.0,
            0.0
        ],
        "mass_diff": [
            0.0,
            0.0,
            0.0,
            0.0,
            0.0,
            0.0,
            0.0
        ],
        "formula": [
            "C15H15NO2",
            "C15H15NO2",
            "C15H15NO2",
            "C15H15NO2",
            "C15H15NO2",
            "C15H15NO2",
            "C15H15NO2"
        ],
        "ions": [
            "[M-H]-",
            "[M-H]-",
            "[M-H]-",
            "[M-H]-",
            "[M-H]-",
            "[M-H]-",
            "[M-H]-"
        ]
    }
}