{
    "cand_form": "C17H19N5O4",
    "cand_ion": "[M+H]+",
    "output_tbl": {
        "mz": [
            0.0,
            51.0229,
            52.0182,
            54.0338,
            62.0151,
            63.0229,
            64.0182,
            64.0308,
            65.026,
            65.0386,
            66.0338,
            67.0291,
            68.0369,
            68.0495,
            75.0229,
            76.0182,
            76.0308,
            77.0386,
            78.0338,
            80.0495,
            81.0447,
            88.0308,
            89.0386,
            90.0338,
            91.0417,
            92.0495,
            95.0491,
            95.0604,
            96.0444,
            102.0338,
            104.0495,
            105.0447,
            114.0338,
            116.0495,
            128.0495,
            129.0447,
            130.04,
            155.0604,
            227.7308
        ],
        "ms2_inten": [
            0.15064920918287633,
            0.4086379091670772,
            0.41114105365769893,
            0.756705058607114,
            0.17623519271266672,
            1.0,
            0.1754640733732974,
            0.22030376494892448,
            0.14265558110215892,
            0.5542370605707597,
            0.325099992903541,
            0.5956776067002254,
            0.5549668569082276,
            0.24466121125165474,
            0.3893290429446742,
            0.14666143874719173,
            0.20818877048153414,
            0.25879455400799534,
            0.3461775712179305,
            0.18965253780178568,
            0.44063571130903967,
            0.15332487355599472,
            0.38910373767282286,
            0.2409871510287091,
            0.18918566526966688,
            0.22829576931310072,
            0.25171866453402986,
            0.12095973621030985,
            0.12802677263266657,
            0.14697228409315577,
            0.1712846284565669,
            0.19829068789802592,
            0.26007925401322274,
            0.13326851511414348,
            0.12590275427298822,
            0.33209493309908206,
            0.20815104243478047,
            0.1320460741249964,
            0.1272254013514812
        ],
        "mono_mass": [
            0.0,
            51.0229,
            52.0182,
            54.0338,
            62.0151,
            63.0229,
            64.0182,
            64.0308,
            65.026,
            65.0386,
            66.0338,
            67.0291,
            68.0369,
            68.0495,
            75.0229,
            76.0182,
            76.0308,
            77.0386,
            78.0338,
            80.0495,
            81.0447,
            88.0308,
            89.0386,
            90.0338,
            91.0417,
            92.0495,
            95.0491,
            95.0604,
            96.0444,
            102.0338,
            104.0495,
            105.0447,
            114.0338,
            116.0495,
            128.0495,
            129.0447,
            130.04,
            155.0604,
            227.7308
        ],
        "abs_mass_diff": [
            0.0,
            0.0,
            0.0,
            0.0,
            0.0,
            0.0,
            0.0,
            0.0,
            0.0,
            0.0,
            0.0,
            0.0,
            0.0,
            0.0,
            0.0,
            0.0,
            0.0,
            0.0,
            0.0,
            0.0,
            0.0,
            0.0,
            0.0,
            0.0,
            0.0,
            0.0,
            0.0,
            0.0,
            0.0,
            0.0,
            0.0,
            0.0,
            0.0,
            0.0,
            0.0,
            0.0,
            0.0,
            0.0,
            0.0
        ],
        "mass_diff": [
            0.0,
            0.0,
            0.0,
            0.0,
            0.0,
            0.0,
            0.0,
            0.0,
            0.0,
            0.0,
            0.0,
            0.0,
            0.0,
            0.0,
            0.0,
            0.0,
            0.0,
            0.0,
            0.0,
            0.0,
            0.0,
            0.0,
            0.0,
            0.0,
            0.0,
            0.0,
            0.0,
            0.0,
            0.0,
            0.0,
            0.0,
            0.0,
            0.0,
            0.0,
            0.0,
            0.0,
            0.0,
            0.0,
            0.0
        ],
        "formula": [
            "C17H19N5O4",
            "C17H19N5O4",
            "C17H19N5O4",
            "C17H19N5O4",
            "C17H19N5O4",
            "C17H19N5O4",
            "C17H19N5O4",
            "C17H19N5O4",
            "C17H19N5O4",
            "C17H19N5O4",
            "C17H19N5O4",
            "C17H19N5O4",
            "C17H19N5O4",
            "C17H19N5O4",
            "C17H19N5O4",
            "C17H19N5O4",
            "C17H19N5O4",
            "C17H19N5O4",
            "C17H19N5O4",
            "C17H19N5O4",
            "C17H19N5O4",
            "C17H19N5O4",
            "C17H19N5O4",
            "C17H19N5O4",
            "C17H19N5O4",
            "C17H19N5O4",
            "C17H19N5O4",
            "C17H19N5O4",
            "C17H19N5O4",
            "C17H19N5O4",
            "C17H19N5O4",
            "C17H19N5O4",
            "C17H19N5O4",
            "C17H19N5O4",
            "C17H19N5O4",
            "C17H19N5O4",
            "C17H19N5O4",
            "C17H19N5O4",
            "C17H19N5O4"
        ],
        "ions": [
            "[M+H]+",
            "[M+H]+",
            "[M+H]+",
            "[M+H]+",
            "[M+H]+",
            "[M+H]+",
            "[M+H]+",
            "[M+H]+",
            "[M+H]+",
            "[M+H]+",
            "[M+H]+",
            "[M+H]+",
            "[M+H]+",
            "[M+H]+",
            "[M+H]+",
            "[M+H]+",
            "[M+H]+",
            "[M+H]+",
            "[M+H]+",
            "[M+H]+",
            "[M+H]+",
            "[M+H]+",
            "[M+H]+",
            "[M+H]+",
            "[M+H]+",
            "[M+H]+",
            "[M+H]+",
            "[M+H]+",
            "[M+H]+",
            "[M+H]+",
            "[M+H]+",
            "[M+H]+",
            "[M+H]+",
            "[M+H]+",
            "[M+H]+",
            "[M+H]+",
            "[M+H]+",
            "[M+H]+",
            "[M+H]+"
        ]
    }
}