{
    "cand_form": "C23H27N5O7S",
    "cand_ion": "[M-H]-",
    "output_tbl": {
        "mz": [
            83.9308,
            98.9293,
            99.9259,
            99.9369,
            116.9402,
            227.7278,
            245.8003,
            507.2401
        ],
        "ms2_inten": [
            0.8540317809450187,
            1.0,
            0.35963441249500494,
            0.6182476497105804,
            0.7094650261982368,
            0.47359588873443564,
            0.19405821636438225,
            0.17813738448734984
        ],
        "mono_mass": [
            83.9308,
            98.9293,
            99.9259,
            99.9369,
            116.9402,
            227.7278,
            245.8003,
            507.2401
        ],
        "abs_mass_diff": [
            0.0,
            0.0,
            0.0,
            0.0,
            0.0,
            0.0,
            0.0,
            0.0
        ],
        "mass_diff": [
            0.0,
            0.0,
            0.0,
            0.0,
            0.0,
            0.0,
            0.0,
            0.0
        ],
        "formula": [
            "C23H27N5O7S",
            "C23H27N5O7S",
            "C23H27N5O7S",
            "C23H27N5O7S",
            "C23H27N5O7S",
            "C23H27N5O7S",
            "C23H27N5O7S",
            "C23H27N5O7S"
        ],
        "ions": [
            "[M-H]-",
            "[M-H]-",
            "[M-H]-",
            "[M-H]-",
            "[M-H]-",
            "[M-H]-",
            "[M-H]-",
            "[M-H]-"
        ]
    }
}