{
    "cand_form": "C15H13N3O3S",
    "cand_ion": "[M-H]-",
    "output_tbl": {
        "mz": [
            0.0,
            61.9884,
            63.9624,
            74.991,
            78.9859,
            227.7254
        ],
        "ms2_inten": [
            1.0,
            0.06844773164652522,
            0.25802148637876465,
            0.04650095453718209,
            0.03765631440990885,
            0.04385289722573761
        ],
        "mono_mass": [
            0.0,
            61.9884,
            63.9624,
            74.991,
            78.9859,
            227.7254
        ],
        "abs_mass_diff": [
            0.0,
            0.0,
            0.0,
            0.0,
            0.0,
            0.0
        ],
        "mass_diff": [
            0.0,
            0.0,
            0.0,
            0.0,
            0.0,
            0.0
        ],
        "formula": [
            "C15H13N3O3S",
            "C15H13N3O3S",
            "C15H13N3O3S",
            "C15H13N3O3S",
            "C15H13N3O3S",
            "C15H13N3O3S"
        ],
        "ions": [
            "[M-H]-",
            "[M-H]-",
            "[M-H]-",
            "[M-H]-",
            "[M-H]-",
            "[M-H]-"
        ]
    }
}