{
    "cand_form": "C18H28ClN",
    "cand_ion": "[M+H]+",
    "output_tbl": {
        "mz": [
            0.0,
            60.0808,
            67.0542,
            69.0699,
            81.0699,
            89.0386,
            103.0542,
            115.0542,
            116.0621,
            125.0153,
            126.0182,
            130.0777,
            139.0309,
            151.0309
        ],
        "ms2_inten": [
            0.08298202505493292,
            0.07293113237783905,
            0.020883349468623275,
            0.027350340186904964,
            0.02010448747651193,
            0.019993844211796785,
            0.1418702879338035,
            0.018237792996310287,
            0.037870798007470924,
            1.0,
            0.03726811011723085,
            0.017084029500539943,
            0.09753119962513579,
            0.021164820867822075
        ],
        "mono_mass": [
            0.0,
            60.0808,
            67.0542,
            69.0699,
            81.0699,
            89.0386,
            103.0542,
            115.0542,
            116.0621,
            125.0153,
            126.0182,
            130.0777,
            139.0309,
            151.0309
        ],
        "abs_mass_diff": [
            0.0,
            0.0,
            0.0,
            0.0,
            0.0,
            0.0,
            0.0,
            0.0,
            0.0,
            0.0,
            0.0,
            0.0,
            0.0,
            0.0
        ],
        "mass_diff": [
            0.0,
            0.0,
            0.0,
            0.0,
            0.0,
            0.0,
            0.0,
            0.0,
            0.0,
            0.0,
            0.0,
            0.0,
            0.0,
            0.0
        ],
        "formula": [
            "C18H28ClN",
            "C18H28ClN",
            "C18H28ClN",
            "C18H28ClN",
            "C18H28ClN",
            "C18H28ClN",
            "C18H28ClN",
            "C18H28ClN",
            "C18H28ClN",
            "C18H28ClN",
            "C18H28ClN",
            "C18H28ClN",
            "C18H28ClN",
            "C18H28ClN"
        ],
        "ions": [
            "[M+H]+",
            "[M+H]+",
            "[M+H]+",
            "[M+H]+",
            "[M+H]+",
            "[M+H]+",
            "[M+H]+",
            "[M+H]+",
            "[M+H]+",
            "[M+H]+",
            "[M+H]+",
            "[M+H]+",
            "[M+H]+",
            "[M+H]+"
        ]
    }
}