{
    "cand_form": "C21H23ClFNO2",
    "cand_ion": "[M+H]+",
    "output_tbl": {
        "mz": [
            54.8608,
            65.0386,
            88.2799,
            89.0386,
            91.0542,
            115.0542,
            165.0699,
            227.7503
        ],
        "ms2_inten": [
            0.5704848177494718,
            0.971088171496586,
            0.4859038695239712,
            0.494667806589406,
            0.7155896236484679,
            0.7466268318513297,
            0.5439961928524345,
            1.0
        ],
        "mono_mass": [
            54.8608,
            65.0386,
            88.2799,
            89.0386,
            91.0542,
            115.0542,
            165.0699,
            227.7503
        ],
        "abs_mass_diff": [
            0.0,
            0.0,
            0.0,
            0.0,
            0.0,
            0.0,
            0.0,
            0.0
        ],
        "mass_diff": [
            0.0,
            0.0,
            0.0,
            0.0,
            0.0,
            0.0,
            0.0,
            0.0
        ],
        "formula": [
            "C21H23ClFNO2",
            "C21H23ClFNO2",
            "C21H23ClFNO2",
            "C21H23ClFNO2",
            "C21H23ClFNO2",
            "C21H23ClFNO2",
            "C21H23ClFNO2",
            "C21H23ClFNO2"
        ],
        "ions": [
            "[M+H]+",
            "[M+H]+",
            "[M+H]+",
            "[M+H]+",
            "[M+H]+",
            "[M+H]+",
            "[M+H]+",
            "[M+H]+"
        ]
    }
}