{
    "cand_form": "C19H22F2N4O3",
    "cand_ion": "[M+H]+",
    "output_tbl": {
        "mz": [
            58.0651,
            84.0808,
            211.0752,
            224.0756,
            230.0724,
            231.0791,
            237.0834,
            251.0865,
            252.0893,
            264.0581,
            265.0608,
            277.0671,
            286.1224,
            292.1256,
            319.1015
        ],
        "ms2_inten": [
            0.296778913301251,
            0.26177218965843896,
            0.07587868809591176,
            0.09066312167162745,
            0.5182158218210944,
            0.27512243126924085,
            0.07756012043167705,
            0.9706870625821543,
            0.09493662387998562,
            1.0,
            0.07448954397330143,
            0.1275770859156224,
            0.14255679530521498,
            0.26465847394647685,
            0.07594111014738271
        ],
        "mono_mass": [
            58.0651,
            84.0808,
            211.0752,
            224.0756,
            230.0724,
            231.0791,
            237.0834,
            251.0865,
            252.0893,
            264.0581,
            265.0608,
            277.0671,
            286.1224,
            292.1256,
            319.1015
        ],
        "abs_mass_diff": [
            0.0,
            0.0,
            0.0,
            0.0,
            0.0,
            0.0,
            0.0,
            0.0,
            0.0,
            0.0,
            0.0,
            0.0,
            0.0,
            0.0,
            0.0
        ],
        "mass_diff": [
            0.0,
            0.0,
            0.0,
            0.0,
            0.0,
            0.0,
            0.0,
            0.0,
            0.0,
            0.0,
            0.0,
            0.0,
            0.0,
            0.0,
            0.0
        ],
        "formula": [
            "C19H22F2N4O3",
            "C19H22F2N4O3",
            "C19H22F2N4O3",
            "C19H22F2N4O3",
            "C19H22F2N4O3",
            "C19H22F2N4O3",
            "C19H22F2N4O3",
            "C19H22F2N4O3",
            "C19H22F2N4O3",
            "C19H22F2N4O3",
            "C19H22F2N4O3",
            "C19H22F2N4O3",
            "C19H22F2N4O3",
            "C19H22F2N4O3",
            "C19H22F2N4O3"
        ],
        "ions": [
            "[M+H]+",
            "[M+H]+",
            "[M+H]+",
            "[M+H]+",
            "[M+H]+",
            "[M+H]+",
            "[M+H]+",
            "[M+H]+",
            "[M+H]+",
            "[M+H]+",
            "[M+H]+",
            "[M+H]+",
            "[M+H]+",
            "[M+H]+",
            "[M+H]+"
        ]
    }
}