{
    "cand_form": "C24H28N2O5",
    "cand_ion": "[M+H]+",
    "output_tbl": {
        "mz": [
            51.0229,
            63.0229,
            65.0386,
            66.0421,
            77.0386,
            89.0386,
            90.0464,
            91.0542,
            92.058,
            95.0491,
            103.0542,
            115.0542,
            117.0573,
            128.0495,
            130.0651
        ],
        "ms2_inten": [
            0.03989441606040676,
            0.07613395069382164,
            1.0,
            0.037438014185422044,
            0.08669611959799631,
            0.08832438800461855,
            0.046758103538053084,
            0.9211951974358186,
            0.03690503191696103,
            0.09569843943725373,
            0.11309489923698807,
            0.19237399792357585,
            0.07462417724708909,
            0.03273134914470369,
            0.33755491409819205
        ],
        "mono_mass": [
            51.0229,
            63.0229,
            65.0386,
            66.0421,
            77.0386,
            89.0386,
            90.0464,
            91.0542,
            92.058,
            95.0491,
            103.0542,
            115.0542,
            117.0573,
            128.0495,
            130.0651
        ],
        "abs_mass_diff": [
            0.0,
            0.0,
            0.0,
            0.0,
            0.0,
            0.0,
            0.0,
            0.0,
            0.0,
            0.0,
            0.0,
            0.0,
            0.0,
            0.0,
            0.0
        ],
        "mass_diff": [
            0.0,
            0.0,
            0.0,
            0.0,
            0.0,
            0.0,
            0.0,
            0.0,
            0.0,
            0.0,
            0.0,
            0.0,
            0.0,
            0.0,
            0.0
        ],
        "formula": [
            "C24H28N2O5",
            "C24H28N2O5",
            "C24H28N2O5",
            "C24H28N2O5",
            "C24H28N2O5",
            "C24H28N2O5",
            "C24H28N2O5",
            "C24H28N2O5",
            "C24H28N2O5",
            "C24H28N2O5",
            "C24H28N2O5",
            "C24H28N2O5",
            "C24H28N2O5",
            "C24H28N2O5",
            "C24H28N2O5"
        ],
        "ions": [
            "[M+H]+",
            "[M+H]+",
            "[M+H]+",
            "[M+H]+",
            "[M+H]+",
            "[M+H]+",
            "[M+H]+",
            "[M+H]+",
            "[M+H]+",
            "[M+H]+",
            "[M+H]+",
            "[M+H]+",
            "[M+H]+",
            "[M+H]+",
            "[M+H]+"
        ]
    }
}