{
    "cand_form": "C12H11N7",
    "cand_ion": "[M+H]+",
    "output_tbl": {
        "mz": [
            92.0243,
            104.0495,
            116.0495,
            141.0447,
            143.0604,
            168.0556,
            183.0665,
            185.0822,
            193.0509,
            195.0665,
            210.0774,
            212.0931,
            220.0618,
            227.104,
            237.0883,
            238.0961,
            254.1149
        ],
        "ms2_inten": [
            0.05568485559512154,
            0.5455744247273235,
            0.06137535853669575,
            0.051531206187404366,
            0.185457122571192,
            0.28340029976139364,
            0.038493107695920195,
            0.05598869950590835,
            0.03233190896588663,
            0.3534161051477491,
            0.16812018236381615,
            0.11416227758803968,
            0.045237610289125034,
            0.035442646036021604,
            1.0,
            0.07262274737596959,
            0.2513984484781394
        ],
        "mono_mass": [
            92.0243,
            104.0495,
            116.0495,
            141.0447,
            143.0604,
            168.0556,
            183.0665,
            185.0822,
            193.0509,
            195.0665,
            210.0774,
            212.0931,
            220.0618,
            227.104,
            237.0883,
            238.0961,
            254.1149
        ],
        "abs_mass_diff": [
            0.0,
            0.0,
            0.0,
            0.0,
            0.0,
            0.0,
            0.0,
            0.0,
            0.0,
            0.0,
            0.0,
            0.0,
            0.0,
            0.0,
            0.0,
            0.0,
            0.0
        ],
        "mass_diff": [
            0.0,
            0.0,
            0.0,
            0.0,
            0.0,
            0.0,
            0.0,
            0.0,
            0.0,
            0.0,
            0.0,
            0.0,
            0.0,
            0.0,
            0.0,
            0.0,
            0.0
        ],
        "formula": [
            "C12H11N7",
            "C12H11N7",
            "C12H11N7",
            "C12H11N7",
            "C12H11N7",
            "C12H11N7",
            "C12H11N7",
            "C12H11N7",
            "C12H11N7",
            "C12H11N7",
            "C12H11N7",
            "C12H11N7",
            "C12H11N7",
            "C12H11N7",
            "C12H11N7",
            "C12H11N7",
            "C12H11N7"
        ],
        "ions": [
            "[M+H]+",
            "[M+H]+",
            "[M+H]+",
            "[M+H]+",
            "[M+H]+",
            "[M+H]+",
            "[M+H]+",
            "[M+H]+",
            "[M+H]+",
            "[M+H]+",
            "[M+H]+",
            "[M+H]+",
            "[M+H]+",
            "[M+H]+",
            "[M+H]+",
            "[M+H]+",
            "[M+H]+"
        ]
    }
}