{
    "cand_form": "C15H13N3O3S",
    "cand_ion": "[M-H]-",
    "output_tbl": {
        "mz": [
            59.0139,
            61.9884,
            63.9624,
            74.991,
            78.9859,
            92.0506,
            114.0561,
            156.0125,
            173.0244,
            227.7177
        ],
        "ms2_inten": [
            1.0,
            0.04856576388734564,
            0.1073327118741206,
            0.02168005039251868,
            0.027622705380118743,
            0.03740168838849856,
            0.05374498053423919,
            0.05911854938787828,
            0.03128934072690455,
            0.02310702185230974
        ],
        "mono_mass": [
            59.0139,
            61.9884,
            63.9624,
            74.991,
            78.9859,
            92.0506,
            114.0561,
            156.0125,
            173.0244,
            227.7177
        ],
        "abs_mass_diff": [
            0.0,
            0.0,
            0.0,
            0.0,
            0.0,
            0.0,
            0.0,
            0.0,
            0.0,
            0.0
        ],
        "mass_diff": [
            0.0,
            0.0,
            0.0,
            0.0,
            0.0,
            0.0,
            0.0,
            0.0,
            0.0,
            0.0
        ],
        "formula": [
            "C15H13N3O3S",
            "C15H13N3O3S",
            "C15H13N3O3S",
            "C15H13N3O3S",
            "C15H13N3O3S",
            "C15H13N3O3S",
            "C15H13N3O3S",
            "C15H13N3O3S",
            "C15H13N3O3S",
            "C15H13N3O3S"
        ],
        "ions": [
            "[M-H]-",
            "[M-H]-",
            "[M-H]-",
            "[M-H]-",
            "[M-H]-",
            "[M-H]-",
            "[M-H]-",
            "[M-H]-",
            "[M-H]-",
            "[M-H]-"
        ]
    }
}