{
    "cand_form": "C20H28N6O4S",
    "cand_ion": "[M+H]+",
    "output_tbl": {
        "mz": [
            58.0651,
            166.0975,
            226.0843,
            227.0927,
            253.072,
            254.0798,
            255.087,
            255.124,
            256.0968,
            283.119,
            284.1261,
            299.1139,
            312.1581,
            331.0873
        ],
        "ms2_inten": [
            0.612487855011508,
            0.0940842865145581,
            0.09742433009715598,
            0.06147856475776563,
            0.12145999347556496,
            0.4341236195932474,
            0.0950519599410681,
            0.2724937552677354,
            0.07183445659346764,
            1.0,
            0.25605877408927796,
            0.13717397943821552,
            0.09501359649863171,
            0.08350212986295154
        ],
        "mono_mass": [
            58.0651,
            166.0975,
            226.0843,
            227.0927,
            253.072,
            254.0798,
            255.087,
            255.124,
            256.0968,
            283.119,
            284.1261,
            299.1139,
            312.1581,
            331.0873
        ],
        "abs_mass_diff": [
            0.0,
            0.0,
            0.0,
            0.0,
            0.0,
            0.0,
            0.0,
            0.0,
            0.0,
            0.0,
            0.0,
            0.0,
            0.0,
            0.0
        ],
        "mass_diff": [
            0.0,
            0.0,
            0.0,
            0.0,
            0.0,
            0.0,
            0.0,
            0.0,
            0.0,
            0.0,
            0.0,
            0.0,
            0.0,
            0.0
        ],
        "formula": [
            "C20H28N6O4S",
            "C20H28N6O4S",
            "C20H28N6O4S",
            "C20H28N6O4S",
            "C20H28N6O4S",
            "C20H28N6O4S",
            "C20H28N6O4S",
            "C20H28N6O4S",
            "C20H28N6O4S",
            "C20H28N6O4S",
            "C20H28N6O4S",
            "C20H28N6O4S",
            "C20H28N6O4S",
            "C20H28N6O4S"
        ],
        "ions": [
            "[M+H]+",
            "[M+H]+",
            "[M+H]+",
            "[M+H]+",
            "[M+H]+",
            "[M+H]+",
            "[M+H]+",
            "[M+H]+",
            "[M+H]+",
            "[M+H]+",
            "[M+H]+",
            "[M+H]+",
            "[M+H]+",
            "[M+H]+"
        ]
    }
}