{
    "cand_form": "C18H23NO3",
    "cand_ion": "[M+H]+",
    "output_tbl": {
        "mz": [
            0.0,
            51.0229,
            53.0386,
            65.0386,
            77.0386,
            79.0542,
            89.0386,
            91.0542,
            94.0413,
            95.0491,
            103.0542,
            105.0445,
            107.0491
        ],
        "ms2_inten": [
            0.1939989559277634,
            1.0,
            0.06906873461087526,
            0.24202555982818524,
            0.709437113965333,
            0.17049021066291262,
            0.0940052992594228,
            0.07622526348227257,
            0.08438926427201465,
            0.7677116848862906,
            0.08315421379952462,
            0.23680776256665412,
            0.15301579703921603
        ],
        "mono_mass": [
            0.0,
            51.0229,
            53.0386,
            65.0386,
            77.0386,
            79.0542,
            89.0386,
            91.0542,
            94.0413,
            95.0491,
            103.0542,
            105.0445,
            107.0491
        ],
        "abs_mass_diff": [
            0.0,
            0.0,
            0.0,
            0.0,
            0.0,
            0.0,
            0.0,
            0.0,
            0.0,
            0.0,
            0.0,
            0.0,
            0.0
        ],
        "mass_diff": [
            0.0,
            0.0,
            0.0,
            0.0,
            0.0,
            0.0,
            0.0,
            0.0,
            0.0,
            0.0,
            0.0,
            0.0,
            0.0
        ],
        "formula": [
            "C18H23NO3",
            "C18H23NO3",
            "C18H23NO3",
            "C18H23NO3",
            "C18H23NO3",
            "C18H23NO3",
            "C18H23NO3",
            "C18H23NO3",
            "C18H23NO3",
            "C18H23NO3",
            "C18H23NO3",
            "C18H23NO3",
            "C18H23NO3"
        ],
        "ions": [
            "[M+H]+",
            "[M+H]+",
            "[M+H]+",
            "[M+H]+",
            "[M+H]+",
            "[M+H]+",
            "[M+H]+",
            "[M+H]+",
            "[M+H]+",
            "[M+H]+",
            "[M+H]+",
            "[M+H]+",
            "[M+H]+"
        ]
    }
}