{
    "cand_form": "C12H18ClNO",
    "cand_ion": "[M+H]+",
    "output_tbl": {
        "mz": [
            0.0,
            63.0229,
            65.0386,
            75.0229,
            77.0386,
            89.0386,
            90.0464,
            91.0542,
            92.0576,
            95.0491,
            102.0464,
            104.0495,
            117.0573,
            118.0651
        ],
        "ms2_inten": [
            0.047201172938830055,
            0.05513455244025947,
            0.6721797056287155,
            0.20690987489855997,
            0.056191217529177925,
            0.1107733401784319,
            0.08333099715503262,
            1.0,
            0.04019224173025462,
            0.053266821151397276,
            0.08689071118629894,
            0.14483681949460142,
            0.179837700234889,
            0.3212468152612797
        ],
        "mono_mass": [
            0.0,
            63.0229,
            65.0386,
            75.0229,
            77.0386,
            89.0386,
            90.0464,
            91.0542,
            92.0576,
            95.0491,
            102.0464,
            104.0495,
            117.0573,
            118.0651
        ],
        "abs_mass_diff": [
            0.0,
            0.0,
            0.0,
            0.0,
            0.0,
            0.0,
            0.0,
            0.0,
            0.0,
            0.0,
            0.0,
            0.0,
            0.0,
            0.0
        ],
        "mass_diff": [
            0.0,
            0.0,
            0.0,
            0.0,
            0.0,
            0.0,
            0.0,
            0.0,
            0.0,
            0.0,
            0.0,
            0.0,
            0.0,
            0.0
        ],
        "formula": [
            "C12H18ClNO",
            "C12H18ClNO",
            "C12H18ClNO",
            "C12H18ClNO",
            "C12H18ClNO",
            "C12H18ClNO",
            "C12H18ClNO",
            "C12H18ClNO",
            "C12H18ClNO",
            "C12H18ClNO",
            "C12H18ClNO",
            "C12H18ClNO",
            "C12H18ClNO",
            "C12H18ClNO"
        ],
        "ions": [
            "[M+H]+",
            "[M+H]+",
            "[M+H]+",
            "[M+H]+",
            "[M+H]+",
            "[M+H]+",
            "[M+H]+",
            "[M+H]+",
            "[M+H]+",
            "[M+H]+",
            "[M+H]+",
            "[M+H]+",
            "[M+H]+",
            "[M+H]+"
        ]
    }
}