{
    "cand_form": "C24H34N6O4S",
    "cand_ion": "[M+H]+",
    "output_tbl": {
        "mz": [
            0.0,
            58.0651,
            63.0229,
            65.0386,
            66.0338,
            67.0291,
            68.0369,
            70.0651,
            72.0808,
            75.0229,
            77.0386,
            81.0447,
            83.0604,
            90.0338,
            91.0417,
            95.0491,
            99.0917,
            103.0417,
            120.0444,
            128.0495,
            129.0447,
            155.0604,
            227.7371
        ],
        "ms2_inten": [
            0.8948748197076059,
            0.15661079322524232,
            0.3627980063595601,
            0.16278178026942772,
            0.09830152712006819,
            0.18770239843641132,
            0.10740674324650515,
            1.0,
            0.38052132781731596,
            0.10238682522963224,
            0.1645764793981294,
            0.09984921147259022,
            0.18653462109708993,
            0.216390284427983,
            0.10568423138069226,
            0.12449956005140575,
            0.33425198103056314,
            0.15925425964159826,
            0.09842530491294857,
            0.12097221969343668,
            0.2517624082899619,
            0.11079143426126041,
            0.11866255717483958
        ],
        "mono_mass": [
            0.0,
            58.0651,
            63.0229,
            65.0386,
            66.0338,
            67.0291,
            68.0369,
            70.0651,
            72.0808,
            75.0229,
            77.0386,
            81.0447,
            83.0604,
            90.0338,
            91.0417,
            95.0491,
            99.0917,
            103.0417,
            120.0444,
            128.0495,
            129.0447,
            155.0604,
            227.7371
        ],
        "abs_mass_diff": [
            0.0,
            0.0,
            0.0,
            0.0,
            0.0,
            0.0,
            0.0,
            0.0,
            0.0,
            0.0,
            0.0,
            0.0,
            0.0,
            0.0,
            0.0,
            0.0,
            0.0,
            0.0,
            0.0,
            0.0,
            0.0,
            0.0,
            0.0
        ],
        "mass_diff": [
            0.0,
            0.0,
            0.0,
            0.0,
            0.0,
            0.0,
            0.0,
            0.0,
            0.0,
            0.0,
            0.0,
            0.0,
            0.0,
            0.0,
            0.0,
            0.0,
            0.0,
            0.0,
            0.0,
            0.0,
            0.0,
            0.0,
            0.0
        ],
        "formula": [
            "C24H34N6O4S",
            "C24H34N6O4S",
            "C24H34N6O4S",
            "C24H34N6O4S",
            "C24H34N6O4S",
            "C24H34N6O4S",
            "C24H34N6O4S",
            "C24H34N6O4S",
            "C24H34N6O4S",
            "C24H34N6O4S",
            "C24H34N6O4S",
            "C24H34N6O4S",
            "C24H34N6O4S",
            "C24H34N6O4S",
            "C24H34N6O4S",
            "C24H34N6O4S",
            "C24H34N6O4S",
            "C24H34N6O4S",
            "C24H34N6O4S",
            "C24H34N6O4S",
            "C24H34N6O4S",
            "C24H34N6O4S",
            "C24H34N6O4S"
        ],
        "ions": [
            "[M+H]+",
            "[M+H]+",
            "[M+H]+",
            "[M+H]+",
            "[M+H]+",
            "[M+H]+",
            "[M+H]+",
            "[M+H]+",
            "[M+H]+",
            "[M+H]+",
            "[M+H]+",
            "[M+H]+",
            "[M+H]+",
            "[M+H]+",
            "[M+H]+",
            "[M+H]+",
            "[M+H]+",
            "[M+H]+",
            "[M+H]+",
            "[M+H]+",
            "[M+H]+",
            "[M+H]+",
            "[M+H]+"
        ]
    }
}